markers/README
markers/get_gtdb_domain_hmms.log
markers/pfam.hmm
markers/pfam.hmm.dat
markers/pfam.hmm.h3f
markers/pfam.hmm.h3i
markers/pfam.hmm.h3m
markers/pfam.hmm.h3p
markers/pfam_ar.lst
markers/pfam_bac.lst
markers/phylum_mg_table_ar.tsv
markers/phylum_mg_table_bac.tsv
markers/tigr_ar.lst
markers/tigr_bac.lst
markers/tigrfam.hmm
unitem/VERSION
unitem/__init__.py
unitem/bin.py
unitem/bin_tools.py
unitem/common.py
unitem/defaults.py
unitem/ensemble.py
unitem/main.py
unitem/markers.py
unitem/plot_common_bases.py
unitem/profile.py
unitem/seq_io.py
unitem/tree_common_bases.py
unitem/utils.py
unitem/external/__init__.py
unitem/external/pfam_search.py
unitem/external/prodigal.py
unitem/external/tigrfam_search.py
unitem/external/tophits.py
unitem/external/pypfam/__init__.py
unitem/external/pypfam/HMM/HMMMatch.py
unitem/external/pypfam/HMM/HMMResults.py
unitem/external/pypfam/HMM/HMMResultsIO.py
unitem/external/pypfam/HMM/HMMSequence.py
unitem/external/pypfam/HMM/HMMUnit.py
unitem/external/pypfam/HMM/__init__.py
unitem/external/pypfam/Scan/PfamScan.py
unitem/external/pypfam/Scan/__init__.py
unitem-1.2.6.data/scripts/unitem
unitem-1.2.6.dist-info/LICENSE
unitem-1.2.6.dist-info/METADATA
unitem-1.2.6.dist-info/WHEEL
unitem-1.2.6.dist-info/top_level.txt
unitem-1.2.6.dist-info/RECORD
