Metadata-Version: 2.1
Name: unitem
Version: 1.2.6
Summary: Ensemble binning strategies for combining the output of multiple binning methods.
Home-page: http://pypi.python.org/pypi/unitem/
Author: Donovan Parks
Author-email: donovan.parks@gmail.com
Maintainer: Donovan Parks
Maintainer-email: donovan.parks@gmail.com
License: GPLv3
Classifier: Development Status :: 4 - Beta
Classifier: License :: OSI Approved :: GNU General Public License v3 (GPLv3)
Classifier: Intended Audience :: Science/Research
Classifier: Natural Language :: English
Classifier: Programming Language :: Python :: 3
Classifier: Topic :: Scientific/Engineering :: Bio-Informatics
License-File: LICENSE
Requires-Dist: numpy (>=1.24)
Requires-Dist: svgwrite (>=1.1.9)
